AIShareTxt/__init__.py
AIShareTxt/ai/__init__.py
AIShareTxt/ai/client.py
AIShareTxt/ai/providers/__init__.py
AIShareTxt/core/__init__.py
AIShareTxt/core/analyzer.py
AIShareTxt/core/config.py
AIShareTxt/core/data_fetcher.py
AIShareTxt/core/report_generator.py
AIShareTxt/docs/AI_INTEGRATION.md
AIShareTxt/docs/README_重构说明.md
AIShareTxt/docs/重构完成总结.md
AIShareTxt/examples/legacy_api.py
AIShareTxt/indicators/__init__.py
AIShareTxt/indicators/technical_indicators.py
AIShareTxt/tests/__init__.py
AIShareTxt/utils/__init__.py
AIShareTxt/utils/stock_list.py
AIShareTxt/utils/utils.py
aishare_txt-2025.11.6.13.dist-info/licenses/LICENSE
aishare_txt-2025.11.6.13.dist-info/METADATA
aishare_txt-2025.11.6.13.dist-info/WHEEL
aishare_txt-2025.11.6.13.dist-info/entry_points.txt
aishare_txt-2025.11.6.13.dist-info/top_level.txt
aishare_txt-2025.11.6.13.dist-info/RECORD
