Metadata-Version: 2.4
Name: aishare-txt
Version: 2025.11.6.13
Summary: 中国股票技术指标文本生成工具包，用于为金融分析相关领域的AI智能体提供上下文服务。
Home-page: https://gitee.com/chaofanat/aishare-txt
Author: AIShareTxt Team
Author-email: chaofanat@gmail.com
License: MIT
Classifier: Development Status :: 4 - Beta
Classifier: Intended Audience :: Financial and Insurance Industry
Classifier: Operating System :: OS Independent
Classifier: Programming Language :: Python :: 3
Classifier: Programming Language :: Python :: 3.10
Classifier: Programming Language :: Python :: 3.11
Classifier: Programming Language :: Python :: 3.12
Classifier: Topic :: Office/Business :: Financial :: Investment
Requires-Python: >=3.10
License-File: LICENSE
Requires-Dist: akshare>=1.9.0
Requires-Dist: TA-Lib>=0.4.26
Requires-Dist: pandas>=1.5.0
Requires-Dist: numpy>=1.21.0
Requires-Dist: requests>=2.28.0
Requires-Dist: pandas_market_calendars>=1.1.0
Requires-Dist: openai>=1.0.0
Requires-Dist: zhipuai>=2.0.0
Provides-Extra: dev
Requires-Dist: pytest>=7.0.0; extra == "dev"
Requires-Dist: pytest-cov>=4.0.0; extra == "dev"
Requires-Dist: black>=22.0.0; extra == "dev"
Requires-Dist: flake8>=5.0.0; extra == "dev"
Requires-Dist: sphinx>=5.0.0; extra == "dev"
Requires-Dist: sphinx-rtd-theme>=1.0.0; extra == "dev"
Requires-Dist: jupyter>=1.0.0; extra == "dev"
Requires-Dist: ipython>=8.0.0; extra == "dev"
Provides-Extra: ai
Requires-Dist: openai>=1.0.0; extra == "ai"
Requires-Dist: zhipuai>=2.0.0; extra == "ai"
Dynamic: author
Dynamic: author-email
Dynamic: classifier
Dynamic: description
Dynamic: description-content-type
Dynamic: home-page
Dynamic: license
Dynamic: license-file
Dynamic: provides-extra
Dynamic: requires-dist
Dynamic: requires-python
Dynamic: summary
